cosmopower/__init__.py
cosmopower/cosmopower_NN.py
cosmopower/cosmopower_PCA.py
cosmopower/cosmopower_PCAplusNN.py
cosmopower/likelihoods/__init__.py
cosmopower/likelihoods/tf_planck2018_lite/__init__.py
cosmopower/likelihoods/tf_planck2018_lite/tf_planck2018_lite.py
cosmopower-0.2.0.dist-info/LICENSE
cosmopower-0.2.0.dist-info/LICENSE_EXT
cosmopower-0.2.0.dist-info/METADATA
cosmopower-0.2.0.dist-info/WHEEL
cosmopower-0.2.0.dist-info/top_level.txt
cosmopower-0.2.0.dist-info/RECORD
