Metadata-Version: 2.1
Name: cosmopower
Version: 0.2.0
Summary: Machine Learning - accelerated Bayesian inference
Home-page: https://github.com/alessiospuriomancini/cosmopower
Author: Alessio Spurio Mancini
Author-email: alessio.spuriomancini@rhul.ac.uk
License: GNU General Public License v3 (GPLv3)
Classifier: Operating System :: OS Independent
Classifier: Intended Audience :: Developers
Classifier: Intended Audience :: Science/Research
License-File: LICENSE
License-File: LICENSE_EXT
Requires-Dist: tensorflow <2.14
Requires-Dist: scikit-learn
Requires-Dist: tqdm
Requires-Dist: pytest
Requires-Dist: tensorflow-probability <0.22
